[        
        {
            "project_id":"Kinderboerderij",
            "created_date":"",
            "extern_intern_project": "intern",                        
            "creator":  [ 
                {
                    "name":"Jules Van Rijsselberge",
                    "specialization": "Crossmedia-ontwerp",
                    "2nd_specialization":"Graphic Design",
                    "jaar":"2de jaar"
                }
            ],
            "text": {
                "title":"Kinderboerderij",
                "description":  [
                    "Als eindwerk voor de tweede jaar ontwikkelden de studenten Graphic Design een huisstijl voor een lokale kinderboerderij.",
                    "Jules Van Rijsselberge ontwierp een sterk, uitgepuurd logo. Een functioneel uithangbord voor de organisatie. Hij combineert in zijn ontwerp een strakke vormgeving met een spontane, kindvriendelijke illustratiestijl gebaseerd op een digitale wasco-techniek."
               ]
            },
            "likes": 0,
            "imagePrimary":"projects/kinderboerderij/3.illustraties.jpg",
            "repo":    {
                "img1": "projects/kinderboerderij/1.logo.jpg",
                "img2": "projects/kinderboerderij/2.uitleglogo.jpg",
                "txt1": "Een inzetbaar logo is voldoende schaalbaar, heeft een beperkt kleurenpalet en vertolkt voldoende de waarden van het merk. De opgegeven witruimte rondom het logo respecteren is een belangrijke factor voor succesvol gebruik",
                "img3": "projects/kinderboerderij/3.illustraties.jpg",
                "txt2": "Digitaal uitgewerkte illustratie",
                "img4": "schetsposter.jpg",
                "txt3": "van ideeschets naar uitgewerkte versie"
            }            
        },
        {
            "project_id":"Orbit",
            "created_date":"",
            "extern_intern_project": "intern",                        
            "creator":  [ 
                {
                    "name":"Siham Asrikh ",
                    "specialization": "Crossmedia-ontwerp",
                    "2nd_specialization":"Graphic Design",
                    "jaar":"2de jaar"
                }
            ],
            "text": {
                "title":"Orbit",
                "description":  [
                   
                ]
            },
            "likes": 0,
            "imagePrimary":"projects/orbit/2.poster.jpg",
            "repo":    {
                "img1": "projects/orbit/1.logo.jpg",
                "img2": "projects/orbit/2.poster.jpg",
                "img3": "projects/orbit/3.advertentie.jpg"
            }            
        }, 
        {
            "project_id":"memorial-van-damme-wv",
            "created_date":"",
            "extern_intern_project": "extern",                        
            "creator":  [ 
                {
                    "name":"Wannes Vansteenhuyse",
                    "specialization": "Crossmedia-ontwerp",
                    "2nd_specialization":"Graphic Design",
                    "jaar":"2de jaar"
                }
            ],
            "text": {
                "title":"Memorial Van Damme",
                "description":  [
                    "De studenten 2CMO namen in 2016 deel aan de wedstrijd die op zoek gaat naar het campagnebeeld voor de 40ste editie van de Memorial Van Damme"
                ]
            },
            "likes": 0,
            "imagePrimary":"projects/memorial-van-damme-wv/2.poster.jpg",
            "repo":    {
                "img1": "projects/memorial-van-damme-wv/2.poster.jpg"
            }            
        },
        {
            "project_id":"Winter",
            "created_date":"",
            "extern_intern_project": "intern",                        
            "creator":  [ 
                {
                    "name":"Freya De Corte",
                    "specialization": "Crossmedia-ontwerp",
                    "2nd_specialization":"Photo Design",
                    "jaar":"2de jaar"
                }
            ],
            "text": {
                "title":"Winter",
                "description":  [
                   
                ]
            },
            "likes": 0,
            "imagePrimary":"projects/winter/detail1_DeCorteFreya.png",
            "repo":    {
                "img1": "projects/winter/detail1_DeCorteFreya.png",
                "txt1": "If you can dream it, we'll learn you how to photoshop it – GDM"
            }            
        }, 
        {
            "project_id":"StreetArtMap",
            "created_date":"",
            "extern_intern_project": "intern",                        
            "creator":  [ 
                {
                    "name":"Bram De Backer",
                    "specialization": "Multimediaproductie",
                    "2nd_specialization":"Audiovisual Design",
                    "jaar":"3de jaar"
                }
            ],
            "text": {
                "title":"StreetArtMap",
                "description":  [
                    "Voor mijn bachelorproef wilde ik een webapplicatie maken die alle street art in België verzamelde en op een interactieve kaart zette. Gebruikers kunnen hun eigen foto's van een mural uploaden, die ma een screening online komen.",
                    "streetartmap.be",
                    [   "360°", 
                        "fotografie",
                        "A-Frame",
                        "Angular",
                        "Firebase",
                        "Sass",
                        "TypeScript",
                        "VR",
                        "Video"
                    ]
                ]
            },
            "likes": 0,
            "imagePrimary":"projects/street-art-map/app-03.png",
            "repo":    {
                "img1": "projects/street-art-map/app-01.png",
                "img2": "projects/street-art-map/app-02.png",
                "img3": "projects/street-art-map/app-03.png",
                "img4": "projects/street-art-map/app-04.png"
            }            
        },
        {
            "project_id":"Heathen",
            "created_date":"",
            "extern_intern_project": "intern", 
            "creator":  [
                {
                    "name":"Lander Denys",
                    "specialization": "Multimediaproductie",
                    "2nd_specialization":"Audiovisual Design",
                    "jaar":"3de jaar"
                }
            ],
            "text": {
                "title":"Heathen",
                "description":  [
                    "Title sequence voor een niet bestaande serie/film."
                ]
            },
            "likes": 0,
            "imagePrimary":"projects/heathen/1.png",
            "repo":    {
                "img1": "projects/heathen/1.png",
                "img2": "projects/heathen/2.png",
                "img3": "projects/heathen/3.png",
                "img4": "projects/heathen/4.png",
                "txt5": "projects/heathen/5.png",
                "img6": "projects/heathen/6.png",
                "vid1": "<iframe src='https://player.vimeo.com/video/209717004?color=ee9900&amp;title=0&amp;byline=0&amp;portrait=0' frameborder='0' webkitallowfullscreen='' mozallowfullscreen='' allowfullscreen=''></iframe>"
            }     
        },
        {
            "project_id":"boef",
            "created_date":"",
            "extern_intern_project": "intern", 
            "creator":  [ 
                {
                    "name":"Jules",
                    "specialization": "Crossmedia",
                    "2nd_specialization":"Graphic",
                    "jaar":"2de jaar"
                }
            ],
            "text": {
                "title":"(B)oef",
                "description":  [
                    "Een dief trekt op pad om zijn slag te slaan ...",
                    "Heel veel ideeën gehad voor dit filmpje, maar helaas opnieuw door de tijdsbeperking van 1 minuut praktisch alle ideeën moeten weggooien! Uiteindelijk wel nog tevreden met het resultaat. Ondertitels kunnen worden aangevinkt, voor diegenen die 'West-Vlaams' onder de categorie 'Zuid-Afrikaans' rekenen …"
                ]
            },
            "likes": 0,
            "imagePrimary":"projects/boef/1.png",
            "repo":    {
                "img1": "projects/boef/1.png",
                "img2": "projects/boef/2.png",
                "img3": "projects/boef/3.png",
                "vid1": "<iframe src='https://player.vimeo.com/video/209717004?color=ee9900&amp;title=0&amp;byline=0&amp;portrait=0' frameborder='0' webkitallowfullscreen='' mozallowfullscreen='' allowfullscreen=''></iframe>"
            }     

        },
        {
            "project_id":"Olympus",
            "created_date":"",
            "extern_intern_project": "intern", 
            "creator":  [
                {
                    "name":"Jens De Wulf",
                    "specialization": "Multimediaproductie",
                    "2nd_specialization":"New Media Development",
                    "jaar":"2de jaar"
                }
            ],
            "text": {
                "title":"Olympus",
                "description":  [
                    "Opdracht: bedenk, ontwerp en programmeer een elektronisch stemsysteem voor verkiezingen en referenda dat bestaat uit een Mobile Web App, een API en een Backoffice en rekening houdt met authenticatie, privacy, beveiliging en integriteit.",
                    [
                        "JavaScript", "Laravel", "MySQL", "PHP", "Vue.js"
                    ]
                ]
            },
            "likes": 0,
            "imagePrimary":"projects/olympus/frontoffice.png",
            "repo": {
                "img1": "projects/olympus/frontoffice.png",
                "txt1": "Web App.",
                "img2": "projects/olympus/backoffice-01.png",
                "txt2": "Dashboard van de backoffice.                ",                
                "img3": "projects/olympus/backoffice-02.png",
                "txt3": "Nieuwe kandidaat ingeven.",
                "img4": "projects/olympus/database.png",
                "txt4": "Databaseschema",
                "img5": "projects/olympus/code.png",
                "txt5": "Laravel- en Vue.js-code."               
                }            
        },
        {
            "project_id":"schoolhoeve",
            "created_date":"",
            "extern_intern_project": "intern", 
            "creator":  [ 
                {
                    "name":"Rietje van hoof",
                    "specialization": "Crossmedia-ontwerp",
                    "2nd_specialization":"Graphic Design",
                    "jaar":"2de jaar"
                }
            ],
            "text": {
                "title":"Schoolhoeve",
                "description":  [
                ]
            },
            "likes": 0,
            "imagePrimary":"projects/schoolhoeve/4.informatieborden.jpg",
            "repo": {
                "img1": "projects/schoolhoeve/1.logo.jpg",
                "img2": "projects/schoolhoeve/2.visual.jpg",
                "img3": "projects/schoolhoeve/3.poster.jpg",
                "img4": "projects/schoolhoeve/4.informatieborden.jpg",
                "img5": "projects/schoolhoeve/5.visual.jpg"
            }            
        },
        {
            "project_id":"Cesar",
            "created_date":"",
            "extern_intern_project": "intern", 
            "creator":  [
                {
                    "name":"Victor Gouhie",
                    "specialization": "Multimediaproductie",
                    "2nd_specialization":"Audiovisual Design",
                    "jaar":"2de jaar"
                }
            ],
            "text": {
                "title":"Cesar",
                "description":  [
                    "De briefing van deze opdracht voor het vak '2D Animatie' luidde als volgt: maak een one minute video door gebruik te maken van ‘Vormator’ elementen."
                ]
            },
            "likes": 0,
            "imagePrimary":"projects/cesar/6_detail_cesar.png",
            "repo": {
                "img1": "projects/cesar/1_detail_theelements.png",
                "txt1": "Vorminator bestaat uit acht vectorvormen, die 'the elements' genoemd worden. Deze mogen door de ontwerpers gebruikt worden om composities te maken, maar je moet je hierbij wel aan een aantal regels houden.",
                "img2": "projects/cesar/2_detail_cesar.png",
                "txt2": "Victor: 'Ik wou kleine elementen gebruiken die samenkomen tot een groot geheel of een groot wezen. De vorminator elementen waren perfect voor dit soort animatie en zo is uiteindelijk de video met het samengestelde skelet tot stand gekomen.'",                
                "img3": "projects/cesar/3_detail_cesar.png",
                "gif1": "projects/cesar/cesar.gif",
                "img4": "projects/cesar/5_detail_cesar.png",
                "txt3": "De bedoeling van de opdracht was om het belang van beperkingen op creativiteit te tonen. De resultaten tonen aan dat je zelfs met een grote hoeveelheid restricties tot een verrassend resultaat kan komen.",
                "img5": "projects/cesar/5_detail_cesar.png",
                "vid1": "<iframe src='https://player.vimeo.com/video/209716825?color=ee9900&amp;title=0&amp;byline=0&amp;portrait=0' frameborder='0' webkitallowfullscreen='' mozallowfullscreen='' allowfullscreen=''></iframe>"
                
            }            
        }, 
        {
            "project_id":"Brussel",
            "created_date":"",
            "extern_intern_project": "intern", 
            "creator":  [
                {
                    "name":"Dean De Coster",
                    "specialization": "Multimediaproductie",
                    "2nd_specialization":"Audiovisual Design",
                    "jaar":"3de jaar"
                }
            ],
            "text": {
                "title":"Brussel XL",
                "description":  [
                    "Deze film werd gemaakt als oefening binnen een leeromgeving en heeft geen enkel commercieel doel.",
                    "Brussel komt niet vaak positief in de kijker en daar wou ik verandering in brengen.<br />Hiervoor maakte ik gebruik van meer dan 1730 beelden.<br />Om de timing goed te doen uitkomen heb ik time-remapping gebruikt.<br />Tot slot om extra accenten te leggen heb ik nog wat animatie toegevoegd.<br />Dit heb ik frame per frame geanimeerd."
                ]
            },
            "likes": 0,
            "imagePrimary":"projects/bxl/detail6_DeCosterDean.png",
            "repo": {
                "img1": "projects/bxl/detail1_DeCosterDean.png",
                "img2": "projects/bxl/detail2_DeCosterDean.png",
                "img3": "projects/bxl/detail3_DeCosterDean.png",
                "img4": "projects/bxl/detail4_DeCosterDean.png",
                "img5": "projects/bxl/detail5_DeCosterDean.png",
                "img6": "projects/bxl/detail6_DeCosterDean.png",
                "vid1": "<iframe src='https://player.vimeo.com/video/209716964?color=ee9900&amp;title=0&amp;byline=0&amp;portrait=0' frameborder='0' webkitallowfullscreen='' mozallowfullscreen='' allowfullscreen=''></iframe>"
            }            
        },
        {
            "project_id":"infografiek",
            "created_date":"",
            "extern_intern_project": "extern",            
            "creator":  [
                {
                    "name":"Elena Vanhauwaert",
                    "specialization": "Crossmedia-ontwerp",
                    "2nd_specialization":"Graphic Design",
                    "jaar":"2de jaar"
                }
            ],
            "text": {
                "title":"Infografiek",
                "description":  [
                    "De studenten CMO visualiseerden de resultaten van een bevraging naar de drijfveren van grafische vormgevers"
                ]
            },
            "likes": 0,
            "imagePrimary":"projects/orbit/2.poster.jpg",
            "repo": {
                "img1": "projects/orbit/1.logo.jpg",
                "img2": "projects/orbit/2.poster.jpg",
                "img3": "projects/orbit/3.advertentie.jpg"
            }            
        },
        {
            "project_id":"Trois_Quarts",
            "extern_intern_project": "intern",            
            "created_date":"",
            "creator":  [
                {
                    "name":"Quinten Braem",
                    "specialization": "Crossmedia-ontwerp",
                    "2nd_specialization":"Photo Design",
                    "jaar": "3de jaar"
                }
            ],
            "text": {
                "title": "Les Trois Quarts",
                "description":  [
                    "Wijn wordt maar al te vaak in een klassieke verpakking verkocht. De studenten 3CMO onderzochten hoe een hedendaagse wijnverpakking er kan uitzien"
                ]
            },
            "likes": 0,
            "imagePrimary": "projects/packshot-wijn/1_logo.jpg",
            "repo": {
                "img1": "projects/packshot-wijn/1_logo.jpg",
                "img2": "projects/packshot-wijn/2_packshot_wijn.jpg",
                "img3": "projects/packshot-wijn/3_packshot_wijn_2.jpg"
            }            
        },
        {
            "project_id":"Irupo",
            "extern_intern_project": "intern",            
            "created_date":"",
            "creator":  [
                {
                    "name":"Kevin De Vuyst",
                    "specialization": "Multimediaproductie",
                    "2nd_specialization":"Audiovisual Design",
                    "jaar":"3de jaar"
                }
            ],
            "text": {
                "title":"IPURO christmas",
                "description":  [
                    "De studenten audiovisual design kregen de opdracht om een 3D packshot te maken. Packshots zie je doorgaans vaak als laatste shot in commercials voor producten."
                ]
            },
            "likes": 0,
            "imagePrimary":"projects/ipuro/3_detail_opstellingzonderachtergr.png",
            "repo": {
                "img1": "projects/ipuro/1_detail_echteflesjes.png",
                "txt1": "De eerste stap was het studiewerk aan de hand van referentiemateriaal. Daarna begint het zogenaamde '3D modellen', via de software de vorm van het onderwerp in de 3 dimensies vastleggen",
                "img2": "projects/ipuro/2_detail_proefopstelling.png",
                "txt2": "Daarna wordt de aandacht gericht op de textuur van het model. Bovenstaande afbeelding toont verschillende opties in een proefopstelling.",
                "img3": "projects/ipuro/3_detail_opstellingzonderachtergr.png",
                "img4": "projects/ipuro/4_detail_finale_opstelling.gif",
                "txt3": "Gepaste animatie en muziek zorgen ervoor dat het plaatje compleet wordt.",
                "vid1": "<iframe src='https://player.vimeo.com/video/209726968?color=ee9900&amp;title=0&amp;byline=0&amp;portrait=0' frameborder='0' webkitallowfullscreen='' mozallowfullscreen='' allowfullscreen=''></iframe>"
            }            
        }, 
        {
            "project_id":"Sociale_bescherming",
            "extern_intern_project": "intern",            
            "created_date":"",
            "creator":  [ 
                {
                    "name":"Yoeri De Sloovere",
                    "specialization": "Crossmedia-ontwerp",
                    "2nd_specialization":"Graphic Design",
                    "jaar":"2de jaar"
                }
            ],
            "text": {
                "title":"Sociale bescherming",
                "description":  [
                    "De tweede jaar CMO maakte in 2016 de wenskaart voor de NGO 'FOS'. Yoeri maakte een grafisch beeld dat perfect vertolkt waar de organisatie voor staat"
                ]
            },
            "likes": 0,
            "imagePrimary":"projects/sociale-bescherming/2.kaart.jpg",
            "repo": {
                "img1": "projects/sociale-bescherming/2.kaart.jpg"
            }            
        },
        {
            "project_id":"vormgever-in-cijfers",
            "extern_intern_project": "intern",            
            "created_date":"",
            "creator":  [
                {
                    "name":"Simon Van Damme",
                    "specialization": "Crossmedia-ontwerp",
                    "2nd_specialization":"Graphic Design",
                    "jaar":"3de jaar"
                }
            ],
            "text": {
                "title":"Vormgever in cijfers",
                "description":  [
                    "De studenten CMO visualiseerden de resultaten van een bevraging naar de drijfveren van grafische vormgevers."
                ]
            },
            "likes": 0,
            "imagePrimary":"projects/vormgever-in-cijfers/3.jpg",
            "repo": {
                "img1": "projects/vormgever-in-cijfers/1.jpg",
                "img2": "projects/vormgever-in-cijfers/2.jpg",
                "txt1": "De bedoeling van een infografiek is om cijfermateriaal te visualiseren zodat de informatie makkelijker verteerbaar wordt voor een breder publiek",
                "img3": "projects/vormgever-in-cijfers/3.jpg"
            }            
        },
        {
            "project_id":"space-dweller",
            "extern_intern_project": "intern",            
            "created_date":"",
            "creator":  [
                {
                    "name":"Jonas Dermul",
                    "specialization": "Crossmedia-ontwerp",
                    "2nd_specialization":"Graphic Design",
                    "jaar":"2de jaar"
                }
            ],
            "text": {
                "title":"Space Dweller",
                "description":  [
                    "Opdracht: 'stel je voor dat een reis naar de planeet Mars even gewoon zou zijn als een intercontinentale vlucht op aarde. Hoe zou je deze reis dan promoten?'"
                ]
            },
            "likes": 0,
                "imagePrimary": "projects/dweller/balk-logo2.png",                
            "repo": {
                "img1": "projects/dweller/balk-logo.png",
                "img2": "projects/dweller/balk-logo2.png",
                "txt1": "Een huisstijl vertrekt vaak vanuit het ontwerp van een logo, dat als basis dient voor de verdere uitwerken van het visuele systeem.",
                "img3": "projects/dweller/balk-visual-poster.png",
                "txt2": "Voor de poster werd een opvallende visual ontworpen als blikvanger.",
                "img4": "projects/dweller/balk-poster.png",
                "txt3": "Het goed afgewogen en bewust beperkt gehouden kleurenpalet zorgt voor visuele binding tussen de elementen in de campagne ",
                "img5": "projects/dweller/balk-visual-buswrap.png",
                "img6": "projects/dweller/balk-buswrap.png"
                
            }            
        },
        {
            "project_id":"kon_samui",
            "extern_intern_project": "intern",            
            "created_date":"",
            "creator":  [ 
                {
                    "name":"Elena Vanhauwaert",
                    "specialization": "Crossmedia-ontwerp",
                    "2nd_specialization":"Graphic-Design",
                    "jaar":"3de jaar"
                }
            ],
            "text": {
                "title":"Kon Samui",
                "description":  [
                    "Een graphic designer moet zich kunnen verplaatsen in de leefwereld van elk soort klant. In dit geval ging om het de wereld van reizen en het promoten van toeristische bestemmingen."
                ]
            },
            "likes": 0,
            "imagePrimary":"projects/kon-samui/1.visual.jpg",
            "repo":    {
                "img1": "projects/kon-samui/1.visual.jpg",
                "img2": "projects/kon-samui/2.poster.jpg"
            }            
        },
        {
            "project_id":"el_dorado",
            "extern_intern_project": "intern",            
            "created_date":"",
            "creator":  [
                {
                    "name":"Amandine Faingnaert",
                    "specialization": "Crossmedia-ontwerp",
                    "2nd_specialization":"Graphic Design",
                    "jaar":"2de jaar"
                }
            ],
            "text": {
                "title":"El Dorado",
                "description":  [
                    "De eindopdracht van de tweede jaar CMO bestond uit het branden van een fictief thema-pretpark. Amandine creëerde het tot de verbeelding sprekende 'El Dorado', een pretpark met piraten-thema"
                ]
            },
            "likes": 0,
            "imagePrimary":"projects/kraken/2.jpg",
            "repo":    {
                "img1": "projects/kraken/1.jpg",
                "img2": "projects/kraken/2.jpg",
                "txt1": "'Branded' communicatie vertrekt in de meeste gevallen vanuit een logo. Een logo kan makkelijk gereproduceerd worden, maar voor het er is worden vele uren besteed aan ontwerpwerk, besprekingen en bijschaven",
                "img3": "projects/kraken/3.jpg",
                "txt2": "Bij de campagne hoorde ook een mascotte",
                "img4": "projects/kraken/4.jpg",
                "img5": "projects/kraken/5.jpg",
                "txt3": "Elk merk heeft een boodschap te verkondigen. Eldorado doet dit onder andere met een postercampagne",
                "img6": "projects/kraken/6.jpg",
                "img7": "projects/kraken/7.jpg",
                "txt4": "Ook tickets en andere praktische toepassingen worden niet vergeten",
                "img8": "projects/kraken/8.jpg",
                "txt5": "Een piraat zonder schatkaart is geen piraat"
            }            
        },
        {
            "project_id":"melk_campagne",
            "extern_intern_project": "intern",            
            "created_date":"",
            "creator":  [ 
                {
                    "name":"Shauny Eloot",
                    "specialization": "Crossmedia-ontwerp",
                    "2nd_specialization":"Photo Design",
                    "jaar":"3de jaar"
                }
            ],
            "text": {
                "title":"Melk Campagne",
                "description":  [
                    "Opdracht: bedenkt een nieuwe merknaam en ontwerp de verpakkingen voor 3 soorten melk. Vol, halfvol en melk met een speciaal smaakje. Er werd een huisstijl uitgewerkt die tevens de basis vormde voor een bijhorende reclamecampagne."
                ]
            },
            "likes": 0,
            "imagePrimary":"projects/milk/2_halfvollogo.png",
            "repo":    {
                "img1": "projects/milk/1_logoevolutie.png",
                "img2": "projects/milk/2_halfvollogo.png",
                "img3": "projects/milk/3_halfvolverpakking.png",
                "txt1": "Kapvorm en photoshop mockup van de halfvolle melk.",                
                "img4": "projects/milk/4_applogo.png",
                "img5": "projects/milk/5_appmockup.png",
                "txt2": "Ontwerp van een promotionele app. Op basis van een ingegeven 'mood' worden melksuggesties aangereikt."                
            }            
        },
        {
            "project_id":"diabeasy",
            "extern_intern_project": "intern",            
            "created_date":"",
            "creator":  [
                {
                    "name":"Stijn Gevens",
                    "specialization": "Crossmedia-ontwerp",
                    "jaar":"2de jaar"
                },
                {
                    "name":"Julie De Clerq",
                    "specialization": "Crossmedia-ontwerp",
                    "jaar":"2de jaar"
                }
            ],
            "text": {
                "title":"Diabeasy",
                "description":  [
                    "Opdracht: bedenk, ontwerp en maak een prototype van een smartwatch- en een smartphone-app, en maak er een promowebsite voor.",
                    "Diabeasy is een app voor diabetici die ervoor moet zorgen dat mensen met diabetes gedurende de hele dag een constante bloedsuikerspiegel hebben en het aantal insuline-injecties zo minimaal mogelijk kunnen houden."

                ],
                "tags":[
                    "Adobe XD",
                    "CSS",
                    "HTML",
                    "JavaScript",
                    "Jekyll",
                    "Markdown",
                    "Sass"
                ]
            },
            "likes": 0,
            "imagePrimary":"Projects/diabeasy/ontwerp-website.png",
            "repo":    {
                "img1": "Projects/diabeasy/ontwerp-website.png",
                "txt1": "Ontwerp voor de promosite die in Jekyll uitgewerkt moet worden.",                
                "img2": "Projects/diabeasy/wireflow-smartphone.jpg",
                "txt2": "Wireflow/Prototype voor de smartphone-app in Adobe XD.",                
                "img3": "Projects/diabeasy/wireflow-smartwatch.jpg",
                "txt3": "Wireflow/Prototype voor de smartwatch-app in Adobe XD."
            }            
        },
        {
            "project_id":"kookboek",
            "extern_intern_project": "Extern",            
            "created_date":"",
            "creator":  [
                {
                    "name":"Elena Vanhauwaert",
                    "specialization": "Crossmedia-ontwerp",
                    "2nd_specialization":"Graphic Design",
                    "jaar":"2de jaar"
                }
            ],
            "text": {
                "title":"Kookboek",
                "description":  [
                    "Ontwerp de cover van een kookboek over Noordzeevis. Hiervoor werkten de studenten met basismateriaal dat ter beschikking werd gesteld door de Gentse Uitgever Borgerhoff en Lamberigts."
                ]
            },
            "likes": 0,
            "imagePrimary":"projects/kookboek/1.cover.png",
            "repo":    {
                "img1": "projects/kookboek/1.cover.png"
            }            
        },
        {
            "project_id":"bourgoyen",
            "extern_intern_project": "intern",            
            "created_date":"",
            "creator":  [
                {
                    "name":"Phaedra De Wambersie",
                    "specialization": "Crossmedia-ontwerp",
                    "2nd_specialization":"Graphic-design",
                    "jaar":"2de jaar"
                }
            ],
            "text": {
                "title":"Huisstijl Bourgoyen",
                "description":  [
                    "De studenten van het 2de jaar CMO kregen de opdracht om het Gentse natuurreservaat De Bourgoyen van een huisstijl te voorzien. Er werd een logo ontwikkeld, een passende illustratiestijl en diverse print- en schermtoepassingen"
                ]
            },
            "likes": 0,
            "imagePrimary":"projects/bourgoyen-pdw/1.logo.jpg",
            "repo":    {
                "img1": "projects/bourgoyen-pdw/1.logo.jpg",
                "img2": "projects/bourgoyen-pdw/2.logonegatief.jpg",
                "img3": "projects/bourgoyen-pdw/3.logonegatief.jpg",
                "img4": "projects/bourgoyen-pdw/4.illustraties.jpg",
                "img5": "projects/bourgoyen-pdw/5.illustraties.jpg"
            }            
        },
        {
            "project_id":"mighty-spicy",
            "extern_intern_project": "intern",            
            "created_date":"",
            "creator":  [ 
                {
                    "name":"Liesbeth Tempelare",
                    "specialization": "Crossmedia-ontwerp",
                    "2nd_specialization":"Graphic Design",
                    "jaar":"2de jaar"
                }
            ],
            "text": {
                "title":"Mighty Spicy",
                "description":  [
                    "In de tweede jaar ontwikkelden de studenten een huisstijl voor een foodtruck-concept. Liesbeth bracht haar pittige taco's via een kleurrijke branding aan de man"
                ]
            },
            "likes": 0,
            "imagePrimary": "projects/mighty-spicy/1_detail_logo.png",
            "repo":    {
                "img1": "projects/mighty-spicy/1_detail_logo.png",
                "txt1": "'Branded' communicatie vertrekt vaak vanuit het logo. Een logo kan makkelijk gereproduceerd worden, maar voor het er is worden vele uren besteed aan ontwerpwerk, besprekingen en bijschaven tot wanneer het helemaal goed zit",
                "img2": "projects/mighty-spicy/2_detail_logovariaties.png",
                "img3": "projects/mighty-spicy/3_detail_foodtruck.png",
                "img4": "projects/mighty-spicy/4_detail_foodtruck.png",
                "txt2": "Een volgende stap is het ontwerpen van de foodtruck zelf. Deze wordt dan later in promotiemateriaal zoals onderstaande advertentie en grondplan verwerkt.",
                "img5": "projects/mighty-spicy/5_detail_advertentie.png",
                "img6": "projects/mighty-spicy/6_detail_plattegrond.png",
                "txt3": "Een brandingcampagne is pas compleet als je de klant ook online kan bereiken.",
                "img7": "projects/mighty-spicy/7_detail_onepage.png"               
            }            
        }  
    ]
